RamseyTheoryRL/__init__.py
RamseyTheoryRL/data/csv/scaled/all_leq6.csv
RamseyTheoryRL/data/csv/scaled/ramsey_3_4.csv
RamseyTheoryRL/data/csv/scaled/ramsey_3_5.csv
RamseyTheoryRL/data/csv/scaled/ramsey_3_6.csv
RamseyTheoryRL/data/csv/scaled/ramsey_3_7.csv
RamseyTheoryRL/data/csv/scaled/ramsey_3_9.csv
RamseyTheoryRL/data/csv/unscaled/all_leq6.csv
RamseyTheoryRL/data/csv/unscaled/ramsey_3_4.csv
RamseyTheoryRL/data/csv/unscaled/ramsey_3_5.csv
RamseyTheoryRL/data/csv/unscaled/ramsey_3_6.csv
RamseyTheoryRL/data/csv/unscaled/ramsey_3_7.csv
RamseyTheoryRL/data/csv/unscaled/ramsey_3_9.csv
RamseyTheoryRL/data/csv/unscaled/ramsey_4_4.csv
RamseyTheoryRL/data/empty_graphs/v35.g6
RamseyTheoryRL/data/empty_graphs/v36.g6
RamseyTheoryRL/data/empty_graphs/v37.g6
RamseyTheoryRL/data/empty_graphs/v38.g6
RamseyTheoryRL/data/empty_graphs/v39.g6
RamseyTheoryRL/data/empty_graphs/v40.g6
RamseyTheoryRL/data/found_counters/r34_graph.g6
RamseyTheoryRL/data/found_counters/r34_isograph.g6
RamseyTheoryRL/data/found_counters/r34_path.txt
RamseyTheoryRL/data/found_counters/r35_graph.g6
RamseyTheoryRL/data/found_counters/r35_path.txt
RamseyTheoryRL/data/found_counters/r39_graph.g6
RamseyTheoryRL/data/found_counters/r3_10_35_isograph.g6
RamseyTheoryRL/data/found_counters/r3_4_6_graph.g6
RamseyTheoryRL/data/found_counters/r3_4_6_isograph.g6
RamseyTheoryRL/data/found_counters/r3_4_7_graph.g6
RamseyTheoryRL/data/found_counters/r3_4_7_isograph.g6
RamseyTheoryRL/data/found_counters/r3_4_7_path.txt
RamseyTheoryRL/data/found_counters/r3_4_8_graph.g6
RamseyTheoryRL/data/found_counters/r3_4_8_isograph.g6
RamseyTheoryRL/data/found_counters/r3_4_8_path.txt
RamseyTheoryRL/data/found_counters/r3_5_12_2_isograph.g6
RamseyTheoryRL/data/found_counters/r3_5_12_isograph.g6
RamseyTheoryRL/data/found_counters/r3_5_3_graph.g6
RamseyTheoryRL/data/found_counters/r3_5_3_isograph.g6
RamseyTheoryRL/data/found_counters/r3_5_3_path.txt
RamseyTheoryRL/data/found_counters/r3_5_6_graph.g6
RamseyTheoryRL-0.83.dist-info/LICENSE.txt
RamseyTheoryRL-0.83.dist-info/METADATA
RamseyTheoryRL-0.83.dist-info/WHEEL
RamseyTheoryRL-0.83.dist-info/top_level.txt
RamseyTheoryRL-0.83.dist-info/RECORD
