Metadata-Version: 2.1
Name: RamseyTheoryRL
Version: 0.83
Summary: Ramsey Number Explorer
Author-email: Steve Vott <svott@usc.edu>, Adam Lehavi <alehavi@usc.edu>
Project-URL: Homepage, https://github.com/aLehav/RamseyTheoryRL
Classifier: Programming Language :: Python :: 3
Classifier: License :: OSI Approved :: MIT License
Classifier: Operating System :: OS Independent
Requires-Python: >=3.10
License-File: LICENSE.txt
